simplex_noise.py
simplex_noise-1.0.0.dist-info/METADATA
simplex_noise-1.0.0.dist-info/WHEEL
simplex_noise-1.0.0.dist-info/entry_points.txt
simplex_noise-1.0.0.dist-info/top_level.txt
simplex_noise-1.0.0.dist-info/RECORD
