Metadata-Version: 2.4
Name: simplex-noise
Version: 1.0.0
Summary: Python wrapper for Pure C Simplex Noise library
Home-page: https://github.com/paredezadrian/simplex-noise
Download-URL: https://github.com/paredezadrian/simplex-noise/archive/v1.0.0.tar.gz
Author: Adrian Paredez
Author-email: adrian@example.com
License: MIT
Project-URL: Bug Tracker, https://github.com/paredezadrian/simplex-noise/issues
Project-URL: Documentation, https://paredezadrian.github.io/simplex-noise/
Project-URL: Source Code, https://github.com/paredezadrian/simplex-noise
Keywords: noise,simplex,procedural,generation,graphics,terrain,texture
Platform: any
Classifier: Development Status :: 5 - Production/Stable
Classifier: Intended Audience :: Developers
Classifier: License :: OSI Approved :: MIT License
Classifier: Operating System :: OS Independent
Classifier: Programming Language :: Python :: 3
Classifier: Programming Language :: Python :: 3.7
Classifier: Programming Language :: Python :: 3.8
Classifier: Programming Language :: Python :: 3.9
Classifier: Programming Language :: Python :: 3.10
Classifier: Programming Language :: Python :: 3.11
Classifier: Programming Language :: Python :: 3.12
Classifier: Programming Language :: C
Classifier: Topic :: Software Development :: Libraries :: Python Modules
Classifier: Topic :: Multimedia :: Graphics
Classifier: Topic :: Scientific/Engineering :: Mathematics
Classifier: Topic :: Games/Entertainment
Requires-Python: >=3.7
Requires-Dist: numpy
Requires-Dist: Pillow
Provides-Extra: dev
Requires-Dist: pytest; extra == "dev"
Requires-Dist: pytest-cov; extra == "dev"
Requires-Dist: matplotlib; extra == "dev"
Requires-Dist: black; extra == "dev"
Requires-Dist: flake8; extra == "dev"
Provides-Extra: docs
Requires-Dist: sphinx; extra == "docs"
Requires-Dist: sphinx-rtd-theme; extra == "docs"
Dynamic: author
Dynamic: author-email
Dynamic: classifier
Dynamic: description
Dynamic: description-content-type
Dynamic: download-url
Dynamic: home-page
Dynamic: keywords
Dynamic: license
Dynamic: platform
Dynamic: project-url
Dynamic: provides-extra
Dynamic: requires-dist
Dynamic: requires-python
Dynamic: summary
